lib_ml_remla24_team02/__init__.py
lib_ml_remla24_team02/data/char_index.joblib
lib_ml_remla24_team02/data_preprocessing.py
lib_ml_remla24_team02-2.0.0.dist-info/METADATA
lib_ml_remla24_team02-2.0.0.dist-info/WHEEL
lib_ml_remla24_team02-2.0.0.dist-info/RECORD
